pyatmo.py
pyatmoshanbs.py
smart_home/Camera.py
smart_home/HomeCoach.py
smart_home/PublicData.py
smart_home/Thermostat.py
smart_home/WeatherStation.py
smart_home/__init__.py
pyatmo_shanbs-1.7.dist-info/LICENSE.txt
pyatmo_shanbs-1.7.dist-info/METADATA
pyatmo_shanbs-1.7.dist-info/WHEEL
pyatmo_shanbs-1.7.dist-info/top_level.txt
pyatmo_shanbs-1.7.dist-info/RECORD
