Metadata-Version: 2.1
Name: pyatmo-shanbs
Version: 1.7
Summary: Simple API to access Netatmo weather station data from any python script. Design for Home-Assitant (but not only)
Home-page: https://github.com/jabesq/netatmo-api-python
Author: Hugo Dupras
Author-email: jabesq@gmail.com
License: MIT
Platform: UNKNOWN
